jbg_util/__init__.py
jbg_util/basic_util.py
jbg_util/binance_models.py
jbg_util/binance_util.py
jbg_util/circular_buffer.py
jbg_util/data_converter.py
jbg_util/database_util.py
jbg_util/file_util.py
jbg_util/input_util.py
jbg_util/logging_util.py
jbg_util/mock_data_util.py
jbg_util/pub_sub_mediator.py
jbg_util/trader_engine.py
jbg_util/trader_models.py
jbg_util/websocket_util.py
jbg_util-2.0.7.dist-info/LICENSE
jbg_util-2.0.7.dist-info/METADATA
jbg_util-2.0.7.dist-info/WHEEL
jbg_util-2.0.7.dist-info/top_level.txt
jbg_util-2.0.7.dist-info/RECORD
