Metadata-Version: 2.1
Name: jbg-util
Version: 2.0.7
Summary: A general util package
Author: Jonathan Gardner
Author-email: jgardnerx85@gmail.com
Classifier: Programming Language :: Python :: 3
Classifier: License :: OSI Approved :: MIT License
Classifier: Operating System :: OS Independent
Requires-Python: >=3.6
License-File: LICENSE
Requires-Dist: tabulate
